pkmodel/__init__.py
pkmodel/__main__.py
pkmodel/model.py
pkmodel/models.py
pkmodel/protocol.py
pkmodel/solution.py
pkmodel/version_info.py
pkmodel/tests/__init__.py
pkmodel/tests/test_model.py
pkmodel/tests/test_protocol.py
pkmodel/tests/test_solution.py
pkmodel_4the_right_side-1.0.2.dist-info/LICENSE
pkmodel_4the_right_side-1.0.2.dist-info/METADATA
pkmodel_4the_right_side-1.0.2.dist-info/WHEEL
pkmodel_4the_right_side-1.0.2.dist-info/top_level.txt
pkmodel_4the_right_side-1.0.2.dist-info/RECORD
