Metadata-Version: 2.1
Name: pkmodel-4the-right-side
Version: 1.0.2
Summary: An example Python project.
Home-page: https://github.com/SABS-R3/2020-software-engineering-projects-pk
Author: 4the-right-side
Author-email: callum.houghton-flory@linacre.ox.ac.uk
Maintainer: Martin Robinson
Maintainer-email: martin.robinson@cs.ox.ac.uk
License: MIT license
License-File: LICENSE
Requires-Dist: numpy
Requires-Dist: matplotlib
Requires-Dist: scipy
Provides-Extra: dev
Requires-Dist: flake8>=3; extra == "dev"
Requires-Dist: pytest; extra == "dev"
Requires-Dist: pytest-cov; extra == "dev"
Provides-Extra: docs
Requires-Dist: sphinx!=1.7.3,>=1.5; extra == "docs"
Requires-Dist: sphinx-rtd-theme; extra == "docs"
